qram/__init__.py
qram-0.0.1.dist-info/LICENSE.txt
qram-0.0.1.dist-info/METADATA
qram-0.0.1.dist-info/WHEEL
qram-0.0.1.dist-info/top_level.txt
qram-0.0.1.dist-info/RECORD
